CHANGES.txt
README.txt
bootstrap.py
buildout.cfg
setup.py
src/z3c/__init__.py
src/z3c.pdftemplate.egg-info/PKG-INFO
src/z3c.pdftemplate.egg-info/SOURCES.txt
src/z3c.pdftemplate.egg-info/dependency_links.txt
src/z3c.pdftemplate.egg-info/namespace_packages.txt
src/z3c.pdftemplate.egg-info/not-zip-safe
src/z3c.pdftemplate.egg-info/requires.txt
src/z3c.pdftemplate.egg-info/top_level.txt
src/z3c/pdftemplate/MAINTAINER.txt
src/z3c/pdftemplate/README.txt
src/z3c/pdftemplate/__init__.py
src/z3c/pdftemplate/configure.zcml
src/z3c/pdftemplate/meta.zcml
src/z3c/pdftemplate/pml.py
src/z3c/pdftemplate/rml.py
src/z3c/pdftemplate/sample.zcml
src/z3c/pdftemplate/tests.py
src/z3c/pdftemplate/z3c.pdftemplate-sample-configure.zcml
src/z3c/pdftemplate/zcml.py
src/z3c/pdftemplate/sample/bopplogo.gif
src/z3c/pdftemplate/sample/box.gif
src/z3c/pdftemplate/sample/dcolner.gif
src/z3c/pdftemplate/sample/devis.rml
src/z3c/pdftemplate/sample/devis_logo.jpg
src/z3c/pdftemplate/sample/dot_blue.gif
src/z3c/pdftemplate/sample/dot_red.gif
src/z3c/pdftemplate/sample/ex01.pt
src/z3c/pdftemplate/sample/ex02.pt
src/z3c/pdftemplate/sample/ex03.pt
src/z3c/pdftemplate/sample/ex04.pt
src/z3c/pdftemplate/sample/ex05.pt
src/z3c/pdftemplate/sample/ex06.pt
src/z3c/pdftemplate/sample/ex07.pt
src/z3c/pdftemplate/sample/ex08.pt
src/z3c/pdftemplate/sample/ex09.pt
src/z3c/pdftemplate/sample/ex10.pt
src/z3c/pdftemplate/sample/ex11.pt
src/z3c/pdftemplate/sample/ex12.pt
src/z3c/pdftemplate/sample/ex13.pt
src/z3c/pdftemplate/sample/ex14.pt
src/z3c/pdftemplate/sample/generic_template.pt
src/z3c/pdftemplate/sample/logo.png
src/z3c/pdftemplate/sample/micromeshfoto.bmp
src/z3c/pdftemplate/sample/micromeshfoto.pt
src/z3c/pdftemplate/sample/micromeshprot.pt
src/z3c/pdftemplate/sample/raylprot.pt
src/z3c/pdftemplate/sample/replogo.gif
src/z3c/pdftemplate/sample/rml_contents.pt
src/z3c/pdftemplate/sample/rollcard.pt
src/z3c/pdftemplate/sample/screenshot.jpg
src/z3c/pdftemplate/sample/thicknessprot.pt
src/z3c/pdftemplate/sample/tiny_logo.png